cows3/__init__.py
cows3/detectorstates.py
cows3/ephemeris.py
cows3/sensitivity.py
cows3/snr.py
cows3-0.0.2.dist-info/LICENSE.md
cows3-0.0.2.dist-info/METADATA
cows3-0.0.2.dist-info/WHEEL
cows3-0.0.2.dist-info/top_level.txt
cows3-0.0.2.dist-info/RECORD
