Metadata-Version: 2.2
Name: cows3
Version: 0.0.2
Summary: Continuous-wave search sensitivity simulator
Author-email: Rodrigo Tenorio <rodrigo.tenorio.marquez@gmail.com>, Lorenzo Mirasola <lorenzo.mirasola@ca.infn.it>
License: MIT License
Project-URL: Homepage, https://github.com/Rodrigo-Tenorio/cows3
Project-URL: Issues, https://github.com/Rodrigo-Tenorio/cows3/issues
Classifier: Programming Language :: Python :: 3
Classifier: License :: OSI Approved :: MIT License
Classifier: Topic :: Scientific/Engineering :: Astronomy
Classifier: Topic :: Scientific/Engineering :: Physics
Requires-Python: >=3.11
License-File: LICENSE.md
Requires-Dist: lalsuite
Requires-Dist: numpy
Requires-Dist: scipy
Requires-Dist: solar_system_ephemerides
Provides-Extra: dev
Requires-Dist: black; extra == "dev"
Requires-Dist: flake8; extra == "dev"
Requires-Dist: pytest; extra == "dev"
